# JMM

## 硬件层数据一致性

协议很多

intel 用MESI

https://www.cnblogs.com/z00377750/p/9180644.html

现代CPU的数据一致性实现 = 缓存锁(MESI ...) + 总线锁

读取缓存以cache line为基本单位，目前64bytes

位于同一缓存行的两个不同数据，被两个不同CPU锁定，产生互相影响的伪共享问题

伪共享问题：JUC/c_028_FalseSharing位于同一缓存行的两个不同的数据，被两个不同的CPU锁定产生（行级别的）互相影响

使用缓存行的对齐能够提高效率

## 乱序问题

CPU为了提高指令执行效率，会在一条指令执行过程中（比如去内存读数据（慢100倍）），去同时执行另一条指令，前提是，两条指令没有依赖关系

https://www.cnblogs.com/liushaodong/p/4777308.html

写操作也可以进行合并 WCBuffer，WriteCombiningBuffer，合并写的机制，这个Buffer比L1还要小还要快，一般只有4个字节。CPU往内存里写
回去数字的时候会首先写到L2，L2太慢，期间CPU里面的这个值又变了，这是可以合并，只把最后结果写回去

https://www.cnblogs.com/liushaodong/p/4777308.html

JUC/029_WriteCombining

乱序执行的证明：JVM/jmm/Disorder.java

原始参考：https://preshing.com/20120515/memory-reordering-caught-in-the-act/

## 如何保证特定情况下不乱序

硬件内存屏障 X86

>  sfence:  store| 在sfence指令前的写操作当必须在sfence指令后的写操作前完成。
>  lfence：load | 在lfence指令前的读操作当必须在lfence指令后的读操作前完成。
>  mfence：modify/mix | 在mfence指令前的读写操作当必须在mfence指令后的读写操作前完成。

> 原子指令，如x86上的”lock …” 指令是一个Full Barrier，执行时会锁住内存子系统来确保执行顺序，甚至跨多个CPU。Software Locks通常使用了内存屏障或原子指令来实现变量可见性和保持程序顺序

l龙芯和ARM对于CPU指令顺序的保障的实现就跟x86不一样

JVM级别如何规范（JSR133）JVM只是个规范，要指望底层的具体实现

> LoadLoad屏障：
>   	对于这样的语句Load1; LoadLoad; Load2， 
>
>  	在Load2及后续读取操作要读取的数据被访问前，保证Load1要读取的数据被读取完毕。
>
> StoreStore屏障：
>
>  	对于这样的语句Store1; StoreStore; Store2，
>	
>  	在Store2及后续写入操作执行前，保证Store1的写入操作对其它处理器可见。
>
> LoadStore屏障：
>
>  	对于这样的语句Load1; LoadStore; Store2，
>	
>  	在Store2及后续写入操作被刷出前，保证Load1要读取的数据被读取完毕。
>
> StoreLoad屏障：
> 	对于这样的语句Store1; StoreLoad; Load2，
>
> ​	 在Load2及后续所有读取操作执行前，保证Store1的写入对所有处理器可见。

volatile的实现细节

volatile就是内存屏障。不过现在有个变成趋势就是不用volatile了，直都接用synchronized，以为后者在java最新的版本中优化了，也不比
volatile差多少

1. 字节码层面
   ACC_VOLATILE

2. JVM层面
   volatile内存区的读写 都加屏障

   > StoreStoreBarrier
   >
   > volatile 写操作
   >
   > StoreLoadBarrier

   > LoadLoadBarrier
   >
   > volatile 读操作
   >
   > LoadStoreBarrier

3. OS和硬件层面
   https://blog.csdn.net/qq_26222859/article/details/52235930
   hsdis - HotSpot Dis Assembler
   windows lock 指令实现 | MESI实现

synchronized实现细节

1. 字节码层面
   ACC_SYNCHRONIZED
   monitorenter monitorexit
   T05_Synchronized的Java汇编：
   ```
    0 aload_0
    1 dup
    2 astore_1
    3 monitorenter
    4 aload_1
    5 monitorexit
    6 goto 14 (+8)
    9 astore_2
   10 aload_1
   11 monitorexit
   12 aload_2
   13 athrow
   14 return
   ```
其中有两条monitorexit，这表示正常和异常情况下都会退出synchronized块
2. JVM层面
   C C++ 调用了操作系统提供的同步机制
3. OS和硬件层面
   X86 : lock cmpxchg / xxx
   lock是锁定其他指令的指令，cmpxchg是对内存某个区域修改的指令，前面有lock说明执行这个指令的时候，这个内存区域被锁定，只有这个指令可以改
   而其他指令不行
   [https](https://blog.csdn.net/21aspnet/article/details/88571740)[://blog.csdn.net/21aspnet/article/details/](https://blog.csdn.net/21aspnet/article/details/88571740)[88571740](https://blog.csdn.net/21aspnet/article/details/88571740)

